.coveragerc
.testr.conf
.tox.oldest.txt
AUTHORS
ChangeLog
LICENSE
MANIFEST.in
README.rst
dev-requirements.txt
requirements.txt
rtfd-requirements.txt
setup.cfg
setup.py
test-requirements.txt
tox.ini
.circleci/config.yml
doc/Makefile
doc/make.bat
doc/api/modules.rst
doc/api/requests_mock.rst
doc/source/adapter.rst
doc/source/conf.py
doc/source/contrib.rst
doc/source/fixture.rst
doc/source/history.rst
doc/source/index.rst
doc/source/knownissues.rst
doc/source/matching.rst
doc/source/mocker.rst
doc/source/overview.rst
doc/source/pytest.rst
doc/source/readme.rst
doc/source/release-notes.rst
doc/source/response.rst
releasenotes/notes/Add-called_once-property-a69546448cbd5542.yaml
releasenotes/notes/Allow-pickling-response-fe751b0a760a5001.yaml
releasenotes/notes/Bump-minimum-requests-2.3-70fd287f6ea1a12e.yaml
releasenotes/notes/add-reset-function-bcef01162cab0912.yaml
releasenotes/notes/additional-matcher-5c5cd466a6d70080.yaml
releasenotes/notes/case-insensitive-matching-a3143221359bbf2d.yaml
releasenotes/notes/explicit-nesting-behaviour-4d28c310dc4c463a.yaml
releasenotes/notes/fix-iter-content-none-1e29754a75273b8c.yaml
releasenotes/notes/fix-pytest-version-discovery-43f27e7e162ed055.yaml
releasenotes/notes/fixture-extras-699a5b5fb5bd6aab.yaml
releasenotes/notes/match-empty-query-string-e6d6976fe002da0b.yaml
releasenotes/notes/pin-requests-version-e0f090aa31dc86c3.yaml
releasenotes/notes/py.test-2-4e7735793288ea2d.yaml
releasenotes/notes/pytest-7e35da8c5f2cd428.yaml
releasenotes/notes/repo-move-15e956e1d54c048b.yaml
releasenotes/notes/request-history-stream-f1d75b33adcd7e97.yaml
releasenotes/notes/session-scoped-mock-7f1c98d9a91bffc8.yaml
releasenotes/notes/set-default-response-reason-f24556261bc7e9e5.yaml
releasenotes/notes/set-real-http-on-mocker-01eb26b65697466d.yaml
releasenotes/notes/user-response-encoding-b2eea39404140164.yaml
requests_mock/__init__.py
requests_mock/adapter.py
requests_mock/compat.py
requests_mock/exceptions.py
requests_mock/mocker.py
requests_mock_df.egg-info/PKG-INFO
requests_mock_df.egg-info/SOURCES.txt
requests_mock_df.egg-info/dependency_links.txt
requests_mock_df.egg-info/entry_points.txt
requests_mock_df.egg-info/not-zip-safe
requests_mock_df.egg-info/pbr.json
requests_mock_df.egg-info/requires.txt
requests_mock_df.egg-info/top_level.txt
